mlabtex/__init__.py
mlabtex/_version.py
mlabtex/core.py
mlabtex-0.2.0.dist-info/LICENSE
mlabtex-0.2.0.dist-info/METADATA
mlabtex-0.2.0.dist-info/WHEEL
mlabtex-0.2.0.dist-info/top_level.txt
mlabtex-0.2.0.dist-info/RECORD
