Metadata-Version: 2.1
Name: mlabtex
Version: 0.2.0
Summary: mlabtex: A renderer for latex code in mayavi.
Home-page: https://github.com/MuellerSeb/mlabtex
Author: Sebastian Mueller
Author-email: info@geostat-framework.org
Maintainer: Sebastian Mueller
Maintainer-email: sebastian.mueller@ufz.de
License: MIT
Platform: Windows
Platform: Linux
Platform: Solaris
Platform: Mac OS-X
Platform: Unix
Classifier: Development Status :: 3 - Alpha
Classifier: Intended Audience :: Developers
Classifier: Intended Audience :: End Users/Desktop
Classifier: Intended Audience :: Science/Research
Classifier: License :: OSI Approved :: MIT License
Classifier: Natural Language :: English
Classifier: Operating System :: MacOS
Classifier: Operating System :: MacOS :: MacOS X
Classifier: Operating System :: Microsoft
Classifier: Operating System :: Microsoft :: Windows
Classifier: Operating System :: POSIX
Classifier: Operating System :: Unix
Classifier: Programming Language :: Python
Classifier: Programming Language :: Python :: 2
Classifier: Programming Language :: Python :: 3
Classifier: Topic :: Scientific/Engineering
Classifier: Topic :: Software Development
Classifier: Topic :: Utilities
Requires-Dist: numpy (>=1.14.5)
Requires-Dist: mayavi (>=4.5.0)
Provides-Extra: all
Requires-Dist: sympy ; extra == 'all'
Requires-Dist: matplotlib ; extra == 'all'
Provides-Extra: matplotlib
Requires-Dist: matplotlib ; extra == 'matplotlib'
Provides-Extra: sympy
Requires-Dist: sympy ; extra == 'sympy'
